{"4":"Dzieci kwiaty","5":"Płonąca żyrafa","6":"Krowa która dużo muczy mało mleka daje","9":"Myszoskoczek","11":"Tu leży pies pogrzebany","14":"Bezkrwawe łowy","23":"Ciężki kawałek chleba","24":"Ciuciubabka","25":"Czajnik bezprzewodowy","31":"Człowiek za burtą","34":"Druga strona barykady","37":"Dziecko wylane z kąpielą","40":"Dziewczyna ratownika","41":"Dziurawe wiadro","42":"Głęboki ukłon","43":"Gołąbek pokoju","46":"Gra w otwarte karty","49":"Historia wyssana z palca","50":"Identyfikacja zwłok","53":"Jęzor lodowcowy","57":"Kapitan iglo","59":"Kącik złamanych serc","60":"Kij w mrowisku","66":"Kotlet z piersi kurczaka","69":"Kropka nad i","70":"Krzyżyk na drogę","73":"Kura znosząca złote jajka","77":"Łóżko piętrowe","79":"Mały deszcz z dużej chmury","82":"Maszynka do mielenia mięsa","84":"Miękkie lądowanie","86":"Miód na sercu","87":"Miód wielokwiatowy","94":"Obstawa prezydenta","96":"Order uśmiechu","101":"Pantomima","102":"Pies z kulawą nogą","106":"Poczta pantoflowa","107":"Pogoda dla bogaczy","111":"Pożeracz serc","112":"Prawa ręka prezydenta","114":"Punkt skupu butelek","120":"Schody do nieba","125":"Słodka chwila","129":"Statki na niebie","130":"Stół obficie zastawiony","131":"Stół z powyłamywanymi nogami","137":"Twardy orzech do gryzienia","140":"Uśmiech od ucha do ucha","141":"Wczasy pod gruszą","143":"Wilk w jagnięcej skórze","145":"Wino kobiety i śpiew","147":"Włosy anielskie","158":"Zamknięty na cztery spusty","159":"Zapalenie opon mózgowych","162":"Złamany grosz","163":"Jak sobie pościelisz tak się wyśpisz","165":"Prawdziwych przyjaciół poznaje się w biedzie","194":"Oczy szeroko zamkniete","195":"Stary człowiek i morze","200":"Gra na cztery rece","201":"Cztery strony świata","205":"Kraina mlekiem i miodem płynaca","207":"Pokoj z widokiem na morze","209":"Wilk w owczej skorze","232":"Chłopcy z placu broni","242":"Pies którego głaszcze kobieta w czerwonej sukni","257":"Droga rowerowa","261":"Skoczek","262":"Linoskoczek","267":"Czasem słońce, czasem deszcz","269":"Jaka to melodia","277":"Lord Vader","287":"Ruchome schody","288":"Podawać czarną polewkę","291":"Zaćmienie słońca","299":"Wakacje z duchami","304":"Czterolistna koniczyna","307":"Kopnąć w kalendarz","316":"Jednorożec","318":"Pojemnik","319":"Nabita lufka","321":"Walet","329":"Nie taki diabeł straszny jak go malują","330":"Kawa na ławę","335":"Siedzący pod jodłą","346":"Skok na bungee","348":"Tłusta kuchnia","349":"Zapiski na pudełku zapałek","351":"As w rękawie","352":"Pantoflarz","358":"Pochwała jest pożyteczniejsza od kary.","359":"Bieda to najlepszy nauczyciel","360":"Skręcić lolka","364":"Mistrz karate","388":"Ręce które leczą","390":"Pilot do telewizora","395":"Pięta Achillesa","398":"Papierowy Tygrys","399":"Mieć głowę na karku","403":"Kulą w płot","404":"Alicja w krainie czarów","407":"Dwóch ludzi z szafą","409":"Kamasutra","416":"Struś pędziwiatr","417":"Przeminęło z wiatrem","421":"Barbórka","422":"Park Jurajski","427":"Zrelaksowane nogi","432":"Zamordowana kredka","440":"Chlopak z gitara","452":"jak dwie krople wody","454":"Z deszczu pod rynnę","455":"Godzina zero","456":"Żar z nieba","458":"zapalenie oskrzeli","461":"Winny się tlumaczy","466":"Zakochany kundel","467":"Romeo i Julia","469":"Akacje","470":"Aleja przyjaźni","475":"Nadzieja matką głupich","477":"Jaki piątek taki świątek","485":"Papierosy","489":"Wielkanoc","491":"Dowcip o teściowej","492":"Straszny film","494":"Cztery pory roku","497":"Wyobraźnia","502":"Jezdziec bez głowy","505":"Wąchac kwiatki od spodu","511":"Siatkowka kobiet","520":"Katecheta","522":"Kurtyzana","524":"Lampa Alladyna","525":"Znaki na niebie","531":"Hot dog","533":"Aligator","536":"Seksmisja","537":"Apetyt rośnie w miarę jedzenia","541":"Być kulą u nogi","542":"Budować zamki na lodzie","544":"Co ma piernik do wiatraka","545":"Co dwie głowy to nie jedna","552":"Czym chata bogata","560":"Gdy kota nie ma, myszy harcują","562":"Gdzie drwa rąbią tam wióry lecą","569":"Hulaj duszo, piekła nie ma","574":"Jaka praca, taka płaca","577":"Jak kamień w wodę","582":"Jak się powiedziało A trzeba powiedzieć B","583":"Jak ty komu tak on tobie","585":"Jednym uchem wchodzi, a drugim wychodzi","586":"Słuchaj uchem a nie brzuchem","587":"Jeśli wejdziesz miedzy wrony, musisz krakać jak i one","595":"Kombinuje jak koń pod górkę","598":"Kto pyta nie błądzi","599":"Leje jak z cebra","606":"Nauka nie poszła w las","610":"Nie ma róży bez kolców","611":"Nie samym chlebem człowiek żyje","619":"Nieszczęścia chodzą parami","623":"Od przybytku głowa nie boli","626":"Porywać się z motyką na słońce","629":"Przyszła koza do woza","631":"Raz na wozie raz pod wozem","632":"Stary ale jary","638":"Ściany mają uszy","641":"Ten się śmieje kto się śmieje ostatni","643":"Trafiła kosa na kamień","646":"Uczepił się jak rzep psiego ogona","648":"Upił się jak świnia","651":"Wybiera się, jak sójka za morze","655":"Złego diabli nie biorą","674":"Siała baba mak i dostała 10 lat","681":"Nawijać makaron na uszy","688":"Każda potwora znajdzie swego amatora","690":"Sierotka Marysia","703":"Mróz na szybie","704":"Światło słoneczne","705":"Pomocna dłoń","709":"Okno na świat","714":"Niedaleko pada jabłko od jabłoni","717":"Szybki jak błyskawica","719":"Mętne spojrzenie","721":"Przemoczony do suchej nitki","722":"Wielka Krokiew","730":"smoczy oddech","733":"Brylant świeci i w popiele ","762":"Co się odwlecze to nie uciecze","764":"Co wolno wojewodzie, to nie tobie smrodzie","785":"Czerwiec stały, grudzień doskonały","786":"Czuć się jak ryba w wodzie","787":"Czym chata bogata tym gościom rada","804":"Syn marnotrawny ","805":"Stary cap","817":"Szczyt Europejski","822":"Chłopaki nie płaczą","826":"Dwunasta godzina","828":"Ryby i dzieci głosu nie mają","829":"Piosenkarz","832":"Matka Boska","837":"Kapuściana głowa","839":"Raz kozie śmierć","841":"Święty Mikołaj","846":"Mydlane oczy","848":"czarne stopy","851":"Biały miś","852":"szybcy i wściekli","855":"Fotel masujący","858":"Dźwięk bębna","859":"Głuchy jak pień","862":"Twarda sztuka","867":"Kieliszek szampana","868":"Ja Cię kocham a Ty śpisz","874":"Nogi z waty","879":"Stare graty","880":"Stara rura","881":"Jesteś szalona","882":"Górski strumyk","885":"Czary mary","888":"czas goi rany","891":"czarno na białym","895":"mina szachisty","897":"miodowe lata","899":"Władca pierścieni","903":"chusteczka haftowana","904":"ciepłe lody","909":"nie życz drugiemu co tobie nie miłe","910":"nie bądź taki szybki Bill","913":"ulica sezamkowa","914":"winobranie","918":"zielono mi..","922":"szczękościsk","924":"ślepa kiszka","929":"małe jest piękne","932":"miękkie nogi","937":"Superman","940":"mycie okna na drabinie","969":"karmić psa","972":"Adrenalina","979":"asystentka","980":"asekuracja","982":"apokalipsa","987":"żart","992":"ziemianin","1001":"cały dom na głowie","1005":"chrzest bojowy","1026":"zestaw głosnomówiacy","1028":"mrówki faraona","1049":"body","1050":"kochaj i tańcz","1051":"Śpiew ptaka","1055":"administrator","1058":"niedźwiedź","1063":"bóbr","1079":"pole magnetyczne","1082":"pełnia księżyca","1086":"zło","1089":"struktura kryształu","1090":"zaklęte rewiry","1092":"marzyciel","1095":"smuga cienia","1098":"niekończąca się opowieść","1099":"krzyk","1100":"siedzi jak trusia","1101":"spóźnieni kochankowie","1107":"przepisy są po to by je łamać","1108":"indochiny","1115":"dżem","1124":"baletnica","1125":"czterej pancerni i pies","1134":"wieczór panieński","1153":"babie lato","1154":"zabawa","1156":"koszykówka","1159":"kanapkowy potwór","1160":"niezapominajka","1164":"pływająca rybka","1166":"pralnia","1168":"świńska grypa","1179":"zestew pierwszej pomocy","1183":"Wyrostek Robaczkowy","1185":"lustro","1194":"x-men","1211":"Goryl","1212":"Muminki","1215":"żarówka","1217":"pierścionek zaręczynowy","1219":"czyste niebo","1220":"Zmierzch","1224":"daleko od noszy","1225":"walizka","1226":"allo allo","1228":"Masz wiadomość","1231":"Asterix i Obelix ","1234":"Kosmiczny mecz","1240":"Taniec z gwiazdami","1245":"Lokomotywa","1247":"Lampka nocna","1257":"Benny Hill","1258":"Shrek","1260":"Król Lew","1262":"lalka","1264":"palec","1266":"Ciotka z Ameryki","1267":"woda mineralna","1268":"Panna z mokrą głową","1270":"Ktokolwiek widział, ktokolwiek wie","1272":"zcinać włosy","1280":"słowotwórstwo","1281":"biurko","1283":"Kamnień spadł z serca","1288":"fala w wojsku","1289":"kopać leżącego","1291":"gorączka sobotniej nocy","1292":"do tanga trzeba dwojga","1293":"obiecanki cacanki","1295":"trening na siłowni","1296":"prawo jazdy","1303":"gwiazda telewizyjna","1317":"kabel","1318":"internet","1331":"Zdrowie","1332":"abstrakcyjne myślenie","1337":"całka","1341":"liryka","1351":"sok z żuka","1357":"śpiewać każdy może","1359":"synonim","1362":"krzywa","1363":"molo","1366":"posejdon","1367":"ruski miesiąc","1372":"marcepan","1376":"fantastyka","1382":"ogromna strata","1387":"gest","1391":"pasza dla świń","1392":"nauka o języku","1398":"słownik przysłów i powiedzeń","1399":"Agata nogą zamiata","1404":"Ambrozja","1417":"Biały kruk","1422":"anonimowy alkoholik","1423":"NASA","1426":"bakteria","1427":"zamach stanu","1428":"chaos","1435":"kochajmy się jak bracia liczmy się jak żydzi","1461":"mleko zostało rozlane","1480":"licho nie śpi","1488":"fatalne zauroczenie","1489":"salami","1498":"Czego oczy nie widzą tego sercu nie żal","1499":"Łatwo przyszło, łatwo poszło. ","1501":"Gdzie kota niema tam myszy charcuja","1505":"gra wstępna","1506":"Kolejka górska","1508":"kto  mieczem wojuje od miecza ginie","1509":"kurcze pieczone","1511":"efekt motyla","1513":"skala ocen","1519":"domek na drzewie","1522":"Owoc","1530":"czerwona planeta","1531":"plac budowy","1533":"helikopter w ogniu","1545":"Grupa trzymająca władzę","1547":"Diabeł ubiera się u Prady","1549":"kalambury","1553":"Harry Potter i kamień filozoficzny","1558":"Harry Potter i Zakon Feniksa","1573":"peruka","1574":"zdumienie","1575":"złota rybka","1577":"puszysta pani","1578":"pluszowy miś ","1579":"huśtawka ","1582":"nie oceniaj książki po okładce","1591":"Bo pić trzeba umieć","1593":"Czy się stoi, czy się leży  jakaś forsa się należy","1597":"balet na oczch","1605":"Charlie i fabryka czekolady","1606":"Epoka lodowcowa","1608":"wszechświat","1609":"dialog","1610":"monolog","1627":"zraniony ptak","1642":"uciekający pan młody","1645":"makaron","1646":"miska","1661":"sąsiedzi","1662":"komunikator ","1664":"Piękna i bestia","1668":"żel","1670":"guzik","1673":"lizak","1674":"państwo","1678":"Telewizor","1679":"wąchać kwiatki od spodu","1688":"Latająca ryba","1690":"staruszka","1701":"więzien","1702":"kaczka dziwaczka","1708":"szumiace drzewa","1716":"małżeński obowiązek","1727":"małżeństwo z rozsądku","1745":"prosić na kolanach","1761":"komputer","1767":"hasło","1768":"hasło w kopercie","1781":"żaba","1787":"przyjaciółka z ławki","1797":"Borat","1813":"gra w ciemno","1814":"akwizytor","1818":"zawód","1821":"sport to zdrowie","1823":"sierota","1826":"szczeżyć kły","1828":"Chałwa","1831":"milczenie owiec","1837":"mamma mia","1841":"matołek","1852":"łowca androidów","1853":"polowanie na kaczki","1854":"fabryka marzeń","1855":"luz blues","1858":"hipopotam","1871":"pokemon","1872":"stare prześcieradło","1875":"szklanka","1891":"dwuwarstwowy","1895":"Włos anielski","1904":"życ jak pies z kotem","1905":"gorąco jak w piekle","1906":"you can dance","1907":"dyrektor","1908":"zakazany owoc","1909":"złej baletnicy przeszkadza rąbek u spódnicy","1919":"bez pasterza stada nie ma","1921":"kijem tego co nie pilnuje swego","1923":"raz dwa trzy","1924":"jaden targuje drugi kupuje","1929":"czego dusza zapragnie","1938":"boso ale w ostrogach","1942":"zmęczenie ciała jest zdrowe dla duszy","1945":"z wielkich wiatrow deszczyk mały","1948":"jaka cena taki towar","1949":"madagaskar","1950":"głód najlepszy kucharz","1956":"baba w progi cisza w nogi","1958":"o wilku mowa","1959":"taniec połamaniec","1969":"miasto","1972":"widelec","1974":"Polak mądry po szkodzie","1976":"wiertarka","1981":"oranżada","1986":"zakwasy","1987":"ślepy i głuchy","1988":"głupi i głupszy","1989":"szansa na sukces","1992":"przepuklina","1996":"siedzieć nad książką","2007":"żelbeton","2008":"kłaczek","2013":"pobocze","2018":"skoki narciarskie","2019":"adam małysz","2028":"góry","2029":"Tatry","2035":"Żyrafa","2037":"opera mydlana","2046":"liść","2050":"Piotruś Pan","2055":"skrawek","2068":"maskotka","2073":"tomcio paluch","2077":"supermarket","2087":"Ucieczka","2093":"Wieża ","2111":"spaghetti","2130":"antena nawigacyjna","2139":"polskie abc","2140":"Wakacyjna przygoda","2142":"kipi kasza kipi groch lepsza kasza niz ten groch","2143":"subkultura","2193":"gimnazium","2202":"złodziejka","2209":"żólte ciżemki","2229":"dziecko w płonącym budynku","2234":"Pulp Fiction","2239":"Sanatorium pod klepsydrą","2271":"hari kriszna","2272":"Nieodebrane połączenie","2273":"Misiu rysiu","2277":"Pies ogrodnika","2296":"Francuski maniciur","2299":"Jazda samochodem","2301":"Wysoki jak brzoza głupi jak koza","2306":"Czas do szkoły","2309":"Słodycze","2310":"hydraulik","2321":"Trzepot skrzydeł","2322":"Ból głowy","2323":"Poranna rosa","2324":"Domek bez adresu","2328":"Robienie ciasta","2329":"Piąte koło u wozu","2339":"Gdy dziecko upada Bóg ręce rozkłada","2358":"Dziewiąta pieczęć","2370":"Kombajn","2385":"Yeti","2392":"Po prostu tańcz","2401":"Organizm","2407":"Kryształ","2412":"Agrafka","2415":"Dywan","2418":"Wróg","2439":"Klan","2441":"Komora gazowa","2445":"Zlewozmywak","2447":"Deska ratunku","2457":"bal sylwestrowy","2460":"Cesarz","2467":"tabernakulum","2470":"menu","2472":"jedzenie","2480":"Zabawa w berka","2481":"datki","2487":"Sieć","2491":"grzyby","2508":"Koło tortur","2510":"widok","2513":"samouczek","2516":"Film erotyczny","2517":"figura geometryczna","2522":"traktor","2523":"pociąg","2525":"linie kolejowe","2530":"poziomka","2532":"grubas","2535":"miś pluszowy","2537":"umięśnienie","2539":"broń","2540":"tlen","2545":"słoneczna pogoda","2546":"deszczowa pogoda","2562":"gang","2563":"członek","2565":"wieczorowa pora","2569":"kocie łby","2575":"ekran","2585":"guma do żucia","2601":"Czarna kredka koloru białego","2604":"pchli targ","2607":"materac wodny","2609":"kolonia","2639":"Depilacja","2645":"buzia","2654":"Świety Mikołaj","2663":"kopiec kreta","2665":"rozdwojenie jaźni","2672":"Pawie oko","2676":"Archiwum X","2690":"uszczelka","2693":"4 wesela i pogrzeb ","2694":"Siała baba mak","2707":"Ślimak, ślimak pokaż rogi dam Ci sera na pierogi","2721":"Informatyk","2729":"Konik na biegunch","2734":"Komiks","2746":"Operator koparki","2747":"Zasoby ludzkie","2753":"Wiktoria","2757":"Łańcuch przczynowo skutkowy","2773":"posąg","2774":"odkurzacz","2782":"klips","2783":"pizza","2784":"ogród zimowy","2795":"głupi jasiu","2810":"rozmowa kwalifikacyjna","2812":"syrena","2813":"tata","2827":"Rybak","2831":"Batman","2833":"Rumcajs","2834":"Żwirek i muchomorek","2836":"Papuga","2838":"Papuga zawsze druga","2860":"Śwpiewać jak ptak","2868":"psia kość","2871":"przekleństwo","2872":"słowik","2885":"czarna owca","2898":"skok w bok","2900":"męczennik","2912":"abrakadabra","2916":"sennik","2917":"damski bokser","2918":"wycieczka krajoznawcza","2928":"Co Ty nie powiesz","2932":"miałczy jak kot","2951":"pieśń","2952":"kultura","2959":"pionek","2965":"Najciemniej pod latarnią","2967":"z sercem na ramieniu","3013":"kręgosłup moralny","3018":"spadająca gwiazda","3019":"mapa nieba","3022":"Ujeżdżać konia","3055":"Okres przejściowy","3061":"Myszka Mickey","3068":"krew z nosa","3071":"Mały dziubek","3075":"Magia i miecz","3081":"Robin hood","3110":"Abecadło","3120":"Pan Hilary","3166":"Poszukiwany, poszukiwana","3170":"Chować głowę w piasek","3179":"Telewizja kablowa","3196":"Rozgrzany jak piec","3202":"Truskawkowe studio","3204":"Wisienka na torcie","3211":"Szukać dziury w całym","3217":"zakupy","3218":"stok","3227":"Walczyć z wiatrakami","3230":"Chłopiec na posyłki","3232":"Uparty jak osioł","3243":"Stary pryk","3244":"Stary piernik","3254":"krzesło","3280":"zsiadłe mleko","3283":"hotel","3300":"Kotek","3305":"Królewna Śnieżka i 7 krasnoludków","3327":"karabin","3331":"Rezystor","3337":"Jak u Pana Boga za piecem","3342":"ciało","3351":"ryba piła","3360":"szatan z 7 klasy","3365":"tatarak","3366":"Kurza melodia","3367":"stokrotka","3370":"Koniec końców","3377":"Lizus","3379":"Dodawanie","3387":"Zbyt duży las","3390":"Leń","3392":"Z małej chmury duży deszcz","3400":"Człowiek człowiekowi wilkiem","3401":"in vino veritas","3412":"Śmieje się jak głupi do sera","3413":"Koszty własne","3419":"wosk pszczeli","3434":"bitwa morska","3447":"zegar ścienny","3481":"dzieciaki górą","3489":"Miarka się przebrała","3493":"Jestem za a nawet przeciw","3494":"Nie chcę ale muszę","3497":"Nad Obręczą","3552":"Płacząca wierzba","3587":"Słownik Języka Polskiego","3604":"oda do radości","3609":"kinomaniak","3660":"bliźniaki jednojajowe","3699":"tańczyła igła z nitką","3710":"pierwszy stopień do piekła","3724":"Nie ma tego złego, co by na dobre nie wyszło","3727":"drzewo genealogiczne","3728":"mur berliński","3750":"z pustego i Salomon nie naleje","3821":"mała ściąga ","3839":"Zbrodnia i kara","3857":"puszka pandory","3920":"miłość jest ślepa","3953":"płatek","3954":"Harcerz","3961":"andrzejki","3974":"wilk i zajac","3975":"występ","3979":"prosiaczek","3980":"hokej","3983":"klawiatura","3992":"sułtan","3994":"kryminalni","3995":"dalmatynczyk","3996":"kotłownia","3997":"budzik","4006":"Pańskie oko konia tuczy","4030":"fotoradar","4037":"Drzwi otwarte","4050":"Reżyser","4095":"Wszyscy mają Mambę, mam i ja!","4100":"Ramka na zdjęcia","4123":"Być albo nie być","4127":"serce z waty","4128":"właściwe tory","4133":"mikser","4146":"Jak kota nie ma to myszy harcują","4152":"Trzepać dywan","4155":"Zielona szkoła","4158":"Śnić na jawie","4167":"Karta miejska","4174":"Pies z kością","4177":"Kapturek","4179":"Stary dziadek","4180":"Czarodziej","4185":"Gwiazda z nieba","4199":"Koparka","4201":"piorun","4221":"Kosmetyczka","4222":"Noworodek","4227":"krem","4228":"Kicz","4239":"roboty na wysokościach","4251":"nóż w sercu","4258":"słoneczny patrol","4264":"MIM","4277":"zbiór zadań","4278":"biblioteka","4284":"obca galaktyka","4368":"Mój brat niedżwiedz","4369":"Ziarnko do ziarnka a zbierze się miarka","4371":"Kropla w morzu","4373":"Wieczny kawaler","4377":"Palenie szkodzi zdrowiu","4379":"Kostka lodu","4396":"Kobieta na krańcu świata","4406":"Przyjaciół poznaje się w biedzie","4408":"Kopalnia soli","4411":"Iść za głosem serca","4458":"Sushi","4496":"od deski do deski","4537":"grawitacja","4549":"rozbój w biały dzień","4553":"gwóźdź programu","4569":"2 gruchające gołąbki na dachu","4588":"piłka ręczna","4609":"miejski zgiełk","4613":"szaleniec","4623":"znak drogowy","4640":"słodki misiu","4641":"klub Go Go","4647":"list od wielbiciela","4664":"Zakupy w markecie","4671":"Wybory Prezydenckie","4687":"brzuchomówca","4695":"wlazł kotek na płotek","4705":"skarbonka","4714":"mrożona herbata","4715":"kawa z mlekiem","4723":"woda gazowana","4739":"Nagi instynkt","4776":"cwany lis","4786":"co ma wisieć, nie utonie","4799":"kula ziemska","4821":"list w butelce","4831":"Małpi gaj","4843":"Wesoły autobus","4851":"wiosenne porządki","4857":"Ciało niebieskie","4867":"Pierwsza gwiazdka","4878":"latający holender","4880":"baśnie tysiąca i jednej nocy","4931":"miss mokrego podkoszulka","4941":"pochmurne niebo","4943":"mysia nora","4952":"człowiek legenda","4969":"Komu w drogę, temu czas","4977":"co mi zrobisz jak mnie złapiesz","4995":"gry hazardowe","5030":"marionetka","5053":"siedmiu samurajów","5057":"lista przebojów","5058":"gumka do włosów","5067":"emancypacja","5099":"bar mleczny","5100":"przez żołądek do serca","5107":"Sabat czarownic","5108":"Zlot motocyklistów","5144":"niemoralna propozycja","5179":"Wziąć nogi za pas","5180":"Złapać srokę za ogon","5182":"Książka telefoniczna","5196":"Zjeść konia z kopytami","5197":"Krokodyle łzy","5198":"Grać na nosie","5199":"Ubrać się od stóp do głów","5205":"Nabić kogoś w butelkę","5210":"Mieć węża w kieszeni","5213":"Sześcian","5218":"Kusza","5227":"Policjantka","5228":"klisza","5229":"Nuta","5237":"Oczy szeroko otwarte","5261":"enigma","5287":"ostatnia godzina","5315":"higiena","5319":"muzyka rockowa","5328":"niedziela","5335":"Jakie jabłko, taka skórka, jaka matka, taka córka.","5361":"kozioł ofiarny","5381":"Rudobrody","7757":"królowa jest tylko jedna","7770":"sex telefon","7772":"dom duchów","7782":"Dom na kurzej nóżce ","7803":"Koń w galopie","7891":"gdy babusia pierze pończoszki to dziadunio zbiera groszki","8023":"człowiek zza biurka","8027":"niebezpieczństwo","12146":"Oogr","12348":"Czarno biały telewizor","14303":"Placek z jabłkami","14364":"Rozjaśnić umysł","16646":"Latorośl","16668":"Kije samobije","16684":"pustka w głowie","16686":"puszcza","16695":"Ile waży słoń trojański","17457":"szalupa ratunkowa ","17458":"stereo","17465":"dożywocie","17475":"oddać hołd","17477":"autostrada","17479":"seryjny morderca","17481":"bal karnawałowy","17492":"paparazzi","17495":"pies najlepszym przyjacielem człowieka","17498":"aparat analogowy","17500":"obedrzeć ze skóry","17501":"postradać zmysły","17503":"muzyka poważna ","17504":"burżuazja ","17508":"Gumisie ","17509":"Papa Smerf","17510":"Żelazna Dama","17513":"aplauz ","17520":"Bój się Boga","17523":"uniwersytet","17526":"Śpieszmy się kochać ludzi, tak szybko odchodzą","17531":"film dla dorosłych","17532":"postprodukcja ","17535":"strach przed lataniem ","17536":"lądowanie awaryjne ","17537":"operacja plastyczna ","17544":"Nawigacja ","17547":"Atak zbrojny ","17574":"Statek kosmiczny","17575":"Sałatka grecka","18303":"ubezpieczenie","18344":"wychowanie fizyczne","18394":"wielkanocny zajączek","18402":"obóz studencki","18405":"gala boksu zawodowego","18408":"pokaż kotku co masz w środku"}